LPAnalysisTK_prototype/__init__.py
LPanalysisTK_prototype-0.0.12.dist-info/LICENSE
LPanalysisTK_prototype-0.0.12.dist-info/METADATA
LPanalysisTK_prototype-0.0.12.dist-info/WHEEL
LPanalysisTK_prototype-0.0.12.dist-info/top_level.txt
LPanalysisTK_prototype-0.0.12.dist-info/RECORD
