Metadata-Version: 2.1
Name: LPanalysisTK-prototype
Version: 0.0.12
Summary: A protoype of a new package in python for Laplacefintools analysis
Author: Nabil Benjaa
Author-email: nabil.benjaa@laplaceinsights.com
Keywords: Analysis,Fintools
Classifier: Development Status :: 1 - Planning
Classifier: Intended Audience :: Science/Research
Classifier: Programming Language :: Python :: 3
Classifier: Operating System :: Unix
Classifier: Operating System :: Microsoft :: Windows
Classifier: License :: OSI Approved :: MIT License
Classifier: Operating System :: OS Independent
License-File: LICENSE
Requires-Dist: pandas
Requires-Dist: numpy
